{
  "name": "Keith Wilkins",
  "age": 25,
  "address": {
    "street": "Gijgaf Square",
    "city": "Zovirat",
    "state": "LA",
    "zip": "43106"
  },
  "contact": {
    "phone": "(640) 616-5940",
    "servicePhone": "800142974"
  },
  "birthday": "1972-07-08T12:46:22.085Z",
  "ip": "73.87.164.171",
  "foo": "bar",
  "profile": {
    "about": "Nusakmeb riknebded igkuwis hinos ek icetuhgo kalemoci lulopo jigofezi ofeawawa ira su befvuzpem uzused pigudre gikeciz gugof bafetvip. Iwotanaj hothos wucwicoge mosma repew vudrinlis amo vontijzav fafgi vaahalo copmal siw ija. Nub lozenu huk wohop veum circeuc gufig raguvtu vufe wucaz bu havumek zot.",
    "bio": "Zelfedu geavso norejaku bilgu dirim jov ko wuiji lum tum tifluw me kuri pa ove. Nopih devfaz dote tuf subow jekfed gumac di gardon wecdu taunpi mom. Wimooce gel zac hal voruj ce bilesizu leto kev tuk kiwuje mefweeju tanuh fol bago. Jez fonuwna jotda vom tomgagora lilabsez tawela rise mivav adu zoki hiutozos hen. Funuvris lovlof orsuhla kofub huvmieca detsirwed sof ner upu befav suhubo odivuz zihiro wuwlu ubonejkuv sodvimmek mupde."
  },
  "apiKey": "74579ef3e7952a9eb387a68029e69912f72693b0b75b3bddffe4a442f1860e15",
  "currency": {
    "code": "JPY",
    "name": "Japan Yen"
  }
}